subseq-1.0.4.dist-info/METADATA
subseq-1.0.4.dist-info/LICENSE
subseq-1.0.4.dist-info/WHEEL
subseq-1.0.4.dist-info/top_level.txt
subseq-1.0.4.dist-info/RECORD
subseq/subseq.cpython-311-x86_64-linux-gnu.so
subseq/alphabet.cpython-311-x86_64-linux-gnu.so
