Metadata-Version: 2.1
Name: subseq
Version: 1.0.4
Summary: Succinct BWT-Based SequencePrediction
Home-page: https://github.com/bluesheeptoken/subseq
Author: Bluesheeptoken
Author-email: louis.fruleux1@gmail.com
License: MIT
Requires-Python: >=3.7, <4
License-File: LICENSE
